MANIFEST.in
README.md
setup.cfg
setup.py
kramlin/__init__.py
kramlin/exceptions.py
kramlin.egg-info/PKG-INFO
kramlin.egg-info/SOURCES.txt
kramlin.egg-info/dependency_links.txt
kramlin.egg-info/not-zip-safe
kramlin.egg-info/top_level.txt
kramlin/mailing/__init__.py
kramlin/mailing/smtp.py
kramlin/mailing/graphql/__init__.py
kramlin/mailing/graphql/enum.py
kramlin/mailing/graphql/inputs.py
kramlin/mailing/graphql/types.py
kramlin/oauth/__init__.py
kramlin/oauth/graphql/__init__.py
kramlin/oauth/graphql/inputs.py
kramlin/oauth/graphql/types.py
kramlin/oauth/utils/__init__.py
kramlin/oauth/utils/client.py
kramlin/oauth/utils/handler.py
kramlin/oauth/utils/provider.py
kramlin/sso/__init__.py
kramlin/sso/graphql/__init__.py
kramlin/sso/graphql/inputs.py
kramlin/sso/graphql/types.py